agentdatashuttle_adspy/__init__.py
agentdatashuttle_adspy/core/__init__.py
agentdatashuttle_adspy/core/client.py
agentdatashuttle_adspy/core/dataconnector.py
agentdatashuttle_adspy/core/notifications.py
agentdatashuttle_adspy/core/publisher.py
agentdatashuttle_adspy/core/subscriber.py
agentdatashuttle_adspy/models/__init__.py
agentdatashuttle_adspy/models/models.py
agentdatashuttle_adspy/utils/__init__.py
agentdatashuttle_adspy/utils/prompts.py
agentdatashuttle_adspy-1.0.4.dist-info/licenses/LICENSE
agentdatashuttle_adspy-1.0.4.dist-info/METADATA
agentdatashuttle_adspy-1.0.4.dist-info/WHEEL
agentdatashuttle_adspy-1.0.4.dist-info/top_level.txt
agentdatashuttle_adspy-1.0.4.dist-info/RECORD
