Metadata-Version: 2.4
Name: agentdatashuttle_adspy
Version: 1.0.4
Summary: Agent Data Shuttle - Python SDK
Author-email: Knowyours <agentdatashuttle@knowyours.co>
License: Apache-2.0
Project-URL: Homepage, https://agentdatashuttle.knowyours.co
Project-URL: Repository, https://github.com/agentdatashuttle/python-sdk
Project-URL: Issues, https://github.com/agentdatashuttle/python-sdk/issues
Requires-Python: >=3.7
License-File: LICENSE
Requires-Dist: langchain
Requires-Dist: langchain-core
Requires-Dist: langchain-community
Requires-Dist: langgraph
Requires-Dist: langgraph-prebuilt
Requires-Dist: python-dotenv
Requires-Dist: requests
Requires-Dist: pydantic
Requires-Dist: pika
Requires-Dist: python-socketio[client]
Requires-Dist: markdown
Requires-Dist: yagmail
Requires-Dist: slackify-markdown
Requires-Dist: slack-sdk
Dynamic: license-file
